up_tamer/__init__.py
up_tamer/converter.py
up_tamer/engine.py
up_tamer-1.1.6.dist-info/licenses/LICENSE
up_tamer-1.1.6.dist-info/METADATA
up_tamer-1.1.6.dist-info/WHEEL
up_tamer-1.1.6.dist-info/top_level.txt
up_tamer-1.1.6.dist-info/RECORD
