Metadata-Version: 2.4
Name: up_tamer
Version: 1.1.6
Summary: up_tamer
Home-page: https://tamer.fbk.eu
Author: FBK Tamer Development Team
Author-email: tamer@fbk.eu
License: APACHE
Requires-Python: >=3.9
License-File: LICENSE
Requires-Dist: pytamer~=0.1.21
Requires-Dist: ConfigSpace
Dynamic: author
Dynamic: author-email
Dynamic: home-page
Dynamic: license
Dynamic: license-file
Dynamic: requires-dist
Dynamic: requires-python
Dynamic: summary
